buidl/__init__.py
buidl/bcur.py
buidl/bech32.py
buidl/bip39_words.txt
buidl/blinding.py
buidl/block.py
buidl/bloomfilter.py
buidl/cecc.py
buidl/chash.py
buidl/compactfilter.py
buidl/descriptor.py
buidl/ecc.py
buidl/hash.py
buidl/hd.py
buidl/helper.py
buidl/libsec_build.py
buidl/libsec_status.py
buidl/merkleblock.py
buidl/mnemonic.py
buidl/network.py
buidl/op.py
buidl/pbkdf2.py
buidl/pecc.py
buidl/phash.py
buidl/psbt.py
buidl/psbt_helper.py
buidl/script.py
buidl/shamir.py
buidl/siphash.py
buidl/slip39_words.txt
buidl/taproot.py
buidl/timelock.py
buidl/tx.py
buidl/witness.py
buidl/test/__init__.py
buidl/test/conftest.py
buidl/test/test_bcur.py
buidl/test/test_bech32.py
buidl/test/test_blinding.py
buidl/test/test_block.py
buidl/test/test_bloomfilter.py
buidl/test/test_compactfilter.py
buidl/test/test_descriptor.py
buidl/test/test_ecc.py
buidl/test/test_hash.py
buidl/test/test_hd.py
buidl/test/test_helper.py
buidl/test/test_merkleblock.py
buidl/test/test_mnemonic.py
buidl/test/test_musig.py
buidl/test/test_network.py
buidl/test/test_op.py
buidl/test/test_pecc.py
buidl/test/test_psbt.py
buidl/test/test_psbt_helper.py
buidl/test/test_schnorr.py
buidl/test/test_script.py
buidl/test/test_shamir.py
buidl/test/test_taproot.py
buidl/test/test_timelock.py
buidl/test/test_tx.py
buidl-0.2.36.data/scripts/multiwallet.py
buidl-0.2.36.data/scripts/singlesweep.py
buidl-0.2.36.dist-info/LICENSE.md
buidl-0.2.36.dist-info/METADATA
buidl-0.2.36.dist-info/WHEEL
buidl-0.2.36.dist-info/top_level.txt
buidl-0.2.36.dist-info/RECORD
