Metadata-Version: 2.1
Name: buidl
Version: 0.2.36
Summary: An easy-to-use and fully featured bitcoin library written in pure python (no dependencies).
Home-page: https://github.com/buidl-bitcoin/buidl-python
Author: Example Author
Author-email: author@example.com
License: UNKNOWN
Platform: UNKNOWN
Classifier: Programming Language :: Python :: 3
Classifier: License :: OSI Approved :: MIT License
Classifier: Operating System :: OS Independent
Requires-Python: >=3.6
License-File: LICENSE.md
